ragify/__init__.py
ragify/cli.py
ragify/config/__init__.py
ragify/config/defaults.py
ragify/core/__init__.py
ragify/core/chunker.py
ragify/core/db_quadrant.py
ragify/core/embedder.py
ragify/core/ragify.py
ragify/utils/__init__.py
ragify/utils/logger.py
ragify_lib-0.1.5.dist-info/licenses/LICENSE
ragify_lib-0.1.5.dist-info/METADATA
ragify_lib-0.1.5.dist-info/WHEEL
ragify_lib-0.1.5.dist-info/entry_points.txt
ragify_lib-0.1.5.dist-info/top_level.txt
ragify_lib-0.1.5.dist-info/RECORD
